step_1/lcd_ctrl.v
module lcd_ctrl (
    input clk,
    input rst,
    input rs,
    input rw,
    input [7:0] datain,
    input start,
    output reg rs_out,
    output reg rw_out,
    output reg enable, 
    output reg [3:0] dataout
);

    localparam IDLE = 2'b00;
    localparam S1   = 2'b01;
    localparam S2   = 2'b10;
    localparam S3   = 2'b11;
    
    reg [1:0] current_state, next_state;
    reg current_rs, next_rs;
    reg current_rw, next_rw;
    reg current_enable, next_enable;
    reg [7:0] current_data, next_data;

    reg [1:0] state;

    always @(posedge clk or posedge rst) begin
        if (rst) begin
            current_state <= IDLE;
            rs_out <= 0;
            rw_out <= 0;
            enable <= 0;
            dataout <= 0;
        end
        else
            current_state <= next_state;
            current_rs <= next_rs;
            current_rw <= next_rw;
            current_data <= next_data;
            current_enable <= next_enable;
    end

    always @(*) begin
        case (current_state)
            IDLE:  next_state = start ? S1 : IDLE;
            S1:    next_state = S2;
            S2:    next_state = S3;
            S3:    next_state = IDLE;
            default: next_state = IDLE;
        endcase

        case (current_state)
            IDLE:  next_rs = start ? rs : current_rs;
            default: next_rs = current_rs;
        endcase

        case (current_state)
            IDLE:  next_rw = start ? rw : current_rw;
            default: next_rw = current_rw;
        endcase 

        case (current_state)
            S2: next_enable = 1;
            default: next_enable = 0;
        endcase

        case (current_state)
            IDLE:  next_data = start ? datain : current_data;
            default: next_data = current_data;
        endcase
    end

    always @(*) begin
        state = current_state;
        rs_out = current_rs;
        rw_out = current_rw;
        enable = current_enable;
        dataout = current_data[7:4];
    end

endmodule

step_1/lcd_ctrl_tb.v
`timescale 1ns/1ns

module lcd_ctrl_tb;

    reg clk, rst, rs, rw, start;
    reg [7:0] datain;

    wire [3:0] dataout;
    wire rs_out, rw_out, enable;

    // Instantiate the FSM
    lcd_ctrl uut (
        .clk(clk),
        .rst(rst),
        .rs(rs),
        .rw(rw),
        .datain(datain),
        .start(start),
        .rs_out(rs_out),
        .rw_out(rw_out),
        .enable(enable),
        .dataout(dataout)
    );

    // Clock generation: 10ns period
    initial clk = 1;
    always #50 clk = ~clk;

    initial begin
        // Dump the waveform to a vcd file for GTKWave
        $dumpfile("lcd_ctrl_tb.vcd");
        $dumpvars(0, lcd_ctrl_tb);
        // Display headers
        $display("Time\tReset\tRS\tRW\tStart\tDatain\tRS_out\tRW_out\tEnable\tDataout");
        $monitor("%g\t%b\t%b\t%b\t%b\t%b\t%b\t%b\t%b\t%b", $time, rst, rs, rw, start, datain, rs_out, rw_out, enable, dataout);

        // Initialize signals
        rst = 0; 
        rs = 0; 
        rw = 0; 
        start = 0; 
        datain = 0;

        // Reset pulse
        #010 {rst, rs, rw, start, datain} = 12'b1_0_0_0_00000000;
        #190 {rst, rs, rw, start, datain} = 12'b0_0_0_0_00000000; // #200

        // Write (1) Data (1) register with A0 
        #100 {rst, rs, rw, start, datain} = 12'b0_1_1_1_10100000;
        #100 {rst, rs, rw, start, datain} = 12'b0_x_x_0_xxxxxxxx;

        #800 $finish;
    end

endmodule

step_1/lcd_ctrl_tb.vcd
$date
	Tue Jun  3 17:55:15 2025
$end
$version
	Icarus Verilog
$end
$timescale
	1ns
$end
$scope module lcd_ctrl_tb $end
$var wire 1 ! rw_out $end
$var wire 1 " rs_out $end
$var wire 1 # enable $end
$var wire 4 $ dataout [3:0] $end
$var reg 1 % clk $end
$var reg 8 & datain [7:0] $end
$var reg 1 ' rs $end
$var reg 1 ( rst $end
$var reg 1 ) rw $end
$var reg 1 * start $end
$scope module uut $end
$var wire 1 % clk $end
$var wire 8 + datain [7:0] $end
$var wire 1 ' rs $end
$var wire 1 ( rst $end
$var wire 1 ) rw $end
$var wire 1 * start $end
$var parameter 2 , IDLE $end
$var parameter 2 - S1 $end
$var parameter 2 . S2 $end
$var parameter 2 / S3 $end
$var reg 8 0 current_data [7:0] $end
$var reg 1 1 current_enable $end
$var reg 1 2 current_rs $end
$var reg 1 3 current_rw $end
$var reg 2 4 current_state [1:0] $end
$var reg 4 5 dataout [3:0] $end
$var reg 1 # enable $end
$var reg 8 6 next_data [7:0] $end
$var reg 1 7 next_enable $end
$var reg 1 8 next_rs $end
$var reg 1 9 next_rw $end
$var reg 2 : next_state [1:0] $end
$var reg 1 " rs_out $end
$var reg 1 ! rw_out $end
$var reg 2 ; state [1:0] $end
$upscope $end
$upscope $end
$enddefinitions $end
$comment Show the parameter values. $end
$dumpall
b11 /
b10 .
b1 -
b0 ,
$end
#0
$dumpvars
bx ;
b0 :
x9
x8
07
bx 6
bx 5
bx 4
x3
x2
x1
bx 0
b0 +
0*
0)
0(
0'
b0 &
1%
bx $
x#
x"
x!
$end
#10
b0 ;
01
bx $
bx 5
0#
x!
x"
b0 4
1(
#50
0%
#100
b0 $
b0 5
0!
0"
1%
#150
0%
#200
1%
0(
#250
0%
#300
b1010 $
b1010 5
1!
1"
b1 ;
b10100000 0
13
12
b1 4
b10100000 6
19
18
b10 :
1%
1'
1)
1*
b10100000 &
b10100000 +
#350
0%
#400
b10 ;
17
b11 :
b10 4
1%
x'
x)
0*
bx &
bx +
#450
0%
#500
1#
b11 ;
07
b0 :
11
b11 4
1%
#550
0%
#600
0#
b0 ;
01
b0 4
1%
